adminsortable/__init__.py
adminsortable/admin.py
adminsortable/fields.py
adminsortable/models.py
adminsortable/utils.py
adminsortable/locale/de/LC_MESSAGES/django.mo
adminsortable/locale/de/LC_MESSAGES/django.po
adminsortable/locale/en/LC_MESSAGES/django.po
adminsortable/locale/es/LC_MESSAGES/django.mo
adminsortable/locale/es/LC_MESSAGES/django.po
adminsortable/locale/hr/LC_MESSAGES/django.mo
adminsortable/locale/hr/LC_MESSAGES/django.po
adminsortable/locale/lv/LC_MESSAGES/django.po
adminsortable/locale/nb/LC_MESSAGES/django.mo
adminsortable/locale/nb/LC_MESSAGES/django.po
adminsortable/locale/nl/LC_MESSAGES/django.mo
adminsortable/locale/nl/LC_MESSAGES/django.po
adminsortable/locale/pl/LC_MESSAGES/django.mo
adminsortable/locale/pl/LC_MESSAGES/django.po
adminsortable/locale/pt_BR/LC_MESSAGES/django.mo
adminsortable/locale/pt_BR/LC_MESSAGES/django.po
adminsortable/locale/ru/LC_MESSAGES/django.mo
adminsortable/locale/ru/LC_MESSAGES/django.po
adminsortable/locale/uk/LC_MESSAGES/django.mo
adminsortable/locale/uk/LC_MESSAGES/django.po
adminsortable/static/adminsortable/css/admin.sortable.css
adminsortable/static/adminsortable/css/admin.sortable.inline.css
adminsortable/static/adminsortable/js/jquery-ui-django-admin.min.js
adminsortable/static/adminsortable/js/jquery.ui.touch-punch.min.js
adminsortable/templates/adminsortable/admin.sortable.html
adminsortable/templates/adminsortable/change_form.html
adminsortable/templates/adminsortable/change_list.html
adminsortable/templates/adminsortable/change_list_with_sort_link.html
adminsortable/templates/adminsortable/csrf/jquery.django-csrf.html
adminsortable/templates/adminsortable/edit_inline/admin.sortable.stacked.inlines.html
adminsortable/templates/adminsortable/edit_inline/admin.sortable.tabular.inlines.html
adminsortable/templates/adminsortable/edit_inline/stacked-1.10.x.html
adminsortable/templates/adminsortable/edit_inline/stacked.html
adminsortable/templates/adminsortable/edit_inline/tabular-1.10.x.html
django_admin_sortable-2.3.dist-info/AUTHORS
django_admin_sortable-2.3.dist-info/METADATA
django_admin_sortable-2.3.dist-info/WHEEL
django_admin_sortable-2.3.dist-info/top_level.txt
django_admin_sortable-2.3.dist-info/RECORD
