Metadata-Version: 2.1
Name: django-admin-sortable
Version: 2.3
Summary: Drag and drop sorting for models and inline models in Django admin.
Home-page: https://github.com/iambrandontaylor/django-admin-sortable
Author: Brandon Taylor
Author-email: alsoicode@gmail.com
License: APL
Platform: UNKNOWN
Classifier: Development Status :: 5 - Production/Stable
Classifier: Environment :: Web Environment
Classifier: Framework :: Django
Classifier: Intended Audience :: Developers
Classifier: License :: OSI Approved :: Apache Software License
Classifier: Operating System :: OS Independent
Classifier: Programming Language :: Python :: 3
Classifier: Topic :: Utilities
Requires-Dist: django
